{
  "assessment_metadata": {
    "source": "step_functions",
    "run_id": "f43fc06b13fe",
    "generated_at": "2026-03-17T21:58:56.243996+00:00",
    "n_emails": 20,
    "n_succeeded": 20,
    "n_failed_exec": 0,
    "dry_run": false,
    "elapsed_seconds": 205.6,
    "state_machine_arn": "arn:aws:states:us-east-1:970850578809:stateMachine:insuremail-ai-dev-email-processing",
    "email_bucket": "insuremail-ai-dev-emails",
    "pass_threshold": 0.7,
    "passed": false,
    "trulens_enabled": false
  },
  "composite_score": 0.6488,
  "dimensions": {
    "intent_classification": {
      "accuracy": 1.0,
      "macro_f1": 1.0,
      "weighted_f1": 1.0,
      "per_class": {
        "payment_issue": {
          "precision": 1.0,
          "recall": 1.0,
          "f1": 1.0,
          "support": 4
        },
        "coverage_query": {
          "precision": 1.0,
          "recall": 1.0,
          "f1": 1.0,
          "support": 2
        },
        "pre_authorisation": {
          "precision": 1.0,
          "recall": 1.0,
          "f1": 1.0,
          "support": 1
        },
        "document_followup": {
          "precision": 1.0,
          "recall": 1.0,
          "f1": 1.0,
          "support": 1
        },
        "claim_submission": {
          "precision": 1.0,
          "recall": 1.0,
          "f1": 1.0,
          "support": 5
        },
        "claim_status": {
          "precision": 1.0,
          "recall": 1.0,
          "f1": 1.0,
          "support": 3
        },
        "id_verification": {
          "precision": 1.0,
          "recall": 1.0,
          "f1": 1.0,
          "support": 1
        },
        "renewal_query": {
          "precision": 1.0,
          "recall": 1.0,
          "f1": 1.0,
          "support": 1
        },
        "policy_change": {
          "precision": 1.0,
          "recall": 1.0,
          "f1": 1.0,
          "support": 2
        }
      },
      "top_confused": [],
      "n_samples": 20,
      "n_correct": 20
    },
    "routing_accuracy": {
      "routing_accuracy": 0.75,
      "correct": 15,
      "total": 20,
      "per_team": {
        "finance_support_team": 1.0,
        "customer_support_team": 0.5,
        "medical_review_team": 0.0,
        "operations_team": 0.0,
        "claims_team": 1.0,
        "renewals_team": 1.0,
        "policy_admin_team": 0.5
      }
    },
    "entity_extraction": {
      "policy_number": {
        "precision": 0.9231,
        "recall": 0.6316,
        "f1": 0.75
      },
      "member_id": {
        "precision": 1.0,
        "recall": 0.2778,
        "f1": 0.4348
      },
      "pii_flag": {
        "precision": 0.0,
        "recall": 0.0,
        "f1": 0.0
      },
      "medical_flag": {
        "precision": 1.0,
        "recall": 0.5833,
        "f1": 0.7368
      }
    },
    "rag_retrieval": {
      "hit_rate": 1.0,
      "mrr": 1.0,
      "ndcg_at_5": 1.0,
      "hits": 20,
      "total": 20,
      "avg_docs_retrieved": 5.0
    },
    "crm_validation": {
      "hit_rate": 0.0,
      "hits": 0,
      "total": 20,
      "eligible": 0,
      "status_counts": {},
      "plan_counts": {}
    },
    "response_quality": {
      "avg_rouge_l": null,
      "rouge_l_coverage": 0.0,
      "hedge_rate": 1.0,
      "escalation_agreement": 0.6667,
      "escalation_pairs_evaluated": 6,
      "n_with_response": 20
    },
    "confidence_calibration": {
      "ece": 0.3126,
      "mae_vs_band": 0.0,
      "band_action_agreement": 0.6667,
      "routing_distribution": {
        "human_review": 0.8,
        "auto_response": 0.2
      },
      "routing_counts": {
        "human_review": 16,
        "auto_response": 4
      },
      "reliability_diagram": [
        {
          "bin_lower": 0.5,
          "bin_upper": 0.6,
          "avg_confidence": 0.5608,
          "avg_accuracy": 1.0,
          "n": 4
        },
        {
          "bin_lower": 0.6,
          "bin_upper": 0.7,
          "avg_confidence": 0.6251,
          "avg_accuracy": 1.0,
          "n": 7
        },
        {
          "bin_lower": 0.7,
          "bin_upper": 0.8,
          "avg_confidence": 0.7707,
          "avg_accuracy": 1.0,
          "n": 5
        },
        {
          "bin_lower": 0.8,
          "bin_upper": 0.9,
          "avg_confidence": 0.8191,
          "avg_accuracy": 1.0,
          "n": 4
        }
      ]
    }
  },
  "per_email_results": [
    {
      "laya_email_id": "EML-000003",
      "sfn_email_id": "728e2a57-5788-4bdf-8588-67480f8d58fb",
      "gold_intent": "payment_issue",
      "gold_route_team": "finance_support_team",
      "gold_requires_human": false,
      "predicted_intent": "payment_issue",
      "predicted_urgency": "medium",
      "predicted_sentiment": "neutral",
      "predicted_route": "finance_support_team",
      "confidence_score": 0.6068,
      "action": "human_review",
      "response_text": "Dear Roisin,\n\nThank you for bringing your billing concern to our attention. To help us better understand and resolve the issue, could you please provide us with the following details:\n\n- Your policy number\n- The date of the transaction in question\n- The amount in question\n\nYou can find this information in your secure Member Area. If you need assistance accessing your Member Area, please let us know.\n\nOnce we have this information, we will investigate the matter and get back to you as soon as pos",
      "rag_hit_count": 5,
      "crm_found": false,
      "crm_policy_status": "",
      "crm_plan_name": "",
      "crm_eligible": false,
      "extracted_policy": "",
      "extracted_member": "",
      "pii_detected": false,
      "medical_detected": false,
      "exec_status": "SUCCEEDED",
      "exec_error": null
    },
    {
      "laya_email_id": "EML-000001",
      "sfn_email_id": "6ca0c3e0-41f9-429e-b250-560435dce586",
      "gold_intent": "coverage_query",
      "gold_route_team": "customer_support_team",
      "gold_requires_human": true,
      "predicted_intent": "coverage_query",
      "predicted_urgency": "medium",
      "predicted_sentiment": "positive",
      "predicted_route": "customer_support_team",
      "confidence_score": 0.7889,
      "action": "human_review",
      "response_text": "\n\n{\n  \"response_text\": \"Dear Sinead,\n\nThank you for contacting Laya Healthcare regarding your upcoming appointment and the potential cost of pain relief medication at Liffey Pharmacy.\n\nBased on the information available to us, we can confirm that the cost of pain relief medication at Liffey Pharmacy may be covered under your current plan, depending on the specific details of your policy and the type of medication prescribed.\n\nTo determine the exact coverage for your situation, we recommend loggi",
      "rag_hit_count": 5,
      "crm_found": false,
      "crm_policy_status": "",
      "crm_plan_name": "",
      "crm_eligible": false,
      "extracted_policy": "POL-IE-821846",
      "extracted_member": "",
      "pii_detected": false,
      "medical_detected": true,
      "exec_status": "SUCCEEDED",
      "exec_error": null
    },
    {
      "laya_email_id": "EML-000004",
      "sfn_email_id": "3ae8883f-f1cd-4a80-83d1-d52b9f19dd17",
      "gold_intent": "payment_issue",
      "gold_route_team": "finance_support_team",
      "gold_requires_human": false,
      "predicted_intent": "payment_issue",
      "predicted_urgency": "medium",
      "predicted_sentiment": "neutral",
      "predicted_route": "finance_support_team",
      "confidence_score": 0.5837,
      "action": "human_review",
      "response_text": "Dear Conor,\n\nThank you for bringing this issue to our attention. We apologize for any inconvenience caused by the payment issue you have experienced. To help resolve this matter, please follow these steps:\n\n1. Log in to your Member Area.\n2. Go to the 'Claims' section and select 'Claims bank details'.\n3. Update your account name and IBAN.\n\nIf you encounter any difficulties, please do not hesitate to contact our team for assistance. We are here to help you manage your health insurance policy with ",
      "rag_hit_count": 5,
      "crm_found": false,
      "crm_policy_status": "",
      "crm_plan_name": "",
      "crm_eligible": false,
      "extracted_policy": "",
      "extracted_member": "",
      "pii_detected": false,
      "medical_detected": false,
      "exec_status": "SUCCEEDED",
      "exec_error": null
    },
    {
      "laya_email_id": "EML-000002",
      "sfn_email_id": "1d3a8fcc-84d7-445e-8256-0d319183efc9",
      "gold_intent": "pre_authorisation",
      "gold_route_team": "medical_review_team",
      "gold_requires_human": true,
      "predicted_intent": "pre_authorisation",
      "predicted_urgency": "medium",
      "predicted_sentiment": "positive",
      "predicted_route": "provider_support_team",
      "confidence_score": 0.8224,
      "action": "auto_response",
      "response_text": "Dear Ciara,\n\nThank you for contacting us regarding your pre-authorisation request for neck strain treatment at Mater Private on or around 28 June 2025. In order to process your request, we require the following information:\n\n- Consultant name\n- Hospital name (Mater Private)\n- Proposed treatment\n- Expected date of treatment\n\nPlease provide this information as soon as possible so that we can expedite the pre-authorisation process. Once we have received this information, we will acknowledge receipt",
      "rag_hit_count": 5,
      "crm_found": false,
      "crm_policy_status": "",
      "crm_plan_name": "",
      "crm_eligible": false,
      "extracted_policy": "POL-IE-859489",
      "extracted_member": "",
      "pii_detected": false,
      "medical_detected": true,
      "exec_status": "SUCCEEDED",
      "exec_error": null
    },
    {
      "laya_email_id": "EML-000005",
      "sfn_email_id": "9ab026c0-967b-49d1-a7fe-ad448d6fa091",
      "gold_intent": "document_followup",
      "gold_route_team": "operations_team",
      "gold_requires_human": false,
      "predicted_intent": "document_followup",
      "predicted_urgency": "medium",
      "predicted_sentiment": "positive",
      "predicted_route": "customer_support_team",
      "confidence_score": 0.6154,
      "action": "human_review",
      "response_text": "Dear Lorcan,\n\nThank you for providing the additional documents for case CASE-771463. We will review them as soon as possible and keep you updated on the progress. If you have any questions or concerns, please do not hesitate to contact us.\n\nRegards,\nYour Health Insurance Team\n\n",
      "rag_hit_count": 5,
      "crm_found": false,
      "crm_policy_status": "",
      "crm_plan_name": "",
      "crm_eligible": false,
      "extracted_policy": "POL-IE-805483",
      "extracted_member": "",
      "pii_detected": false,
      "medical_detected": false,
      "exec_status": "SUCCEEDED",
      "exec_error": null
    },
    {
      "laya_email_id": "EML-000008",
      "sfn_email_id": "f45c393a-25f6-497b-8f56-ecba1fd8df89",
      "gold_intent": "claim_submission",
      "gold_route_team": "claims_team",
      "gold_requires_human": false,
      "predicted_intent": "claim_submission",
      "predicted_urgency": "medium",
      "predicted_sentiment": "positive",
      "predicted_route": "claims_team",
      "confidence_score": 0.6463,
      "action": "human_review",
      "response_text": "Dear Maeve,\n\nThank you for submitting your claim for neck strain treatment on 11 May 2025 at City Sports Injury Clinic. We appreciate your prompt attention to this matter.\n\nTo process your claim, please follow the steps outlined in our 'How to Claim' knowledge base article. You can submit your claim through the Laya App or your Member Area at any time, day or night. This process is simple and convenient, allowing you to take a photo of your receipt using your phone and submit it through the App.",
      "rag_hit_count": 5,
      "crm_found": false,
      "crm_policy_status": "",
      "crm_plan_name": "",
      "crm_eligible": false,
      "extracted_policy": "POL-IE-223694",
      "extracted_member": "",
      "pii_detected": false,
      "medical_detected": true,
      "exec_status": "SUCCEEDED",
      "exec_error": null
    },
    {
      "laya_email_id": "EML-000006",
      "sfn_email_id": "d3fee841-c244-438a-89f7-8cb8a0fe3014",
      "gold_intent": "claim_submission",
      "gold_route_team": "claims_team",
      "gold_requires_human": false,
      "predicted_intent": "claim_submission",
      "predicted_urgency": "medium",
      "predicted_sentiment": "positive",
      "predicted_route": "claims_team",
      "confidence_score": 0.7825,
      "action": "human_review",
      "response_text": "Dear Aoife,\n\nThank you for submitting your claim for the dermatology consultation on 22 July 2025 at Beacon Medical Centre. We appreciate your prompt attention to this matter.\n\nHowever, we would like to inform you that we cannot process your claim through email. In accordance with our policy, all claims must be submitted through our App or Member Area.\n\nTo submit your claim, please follow the steps outlined in our 'How to Claim' guide, which can be found on our website at https://www.layahealthc",
      "rag_hit_count": 5,
      "crm_found": false,
      "crm_policy_status": "",
      "crm_plan_name": "",
      "crm_eligible": false,
      "extracted_policy": "",
      "extracted_member": "MEM-000965",
      "pii_detected": false,
      "medical_detected": false,
      "exec_status": "SUCCEEDED",
      "exec_error": null
    },
    {
      "laya_email_id": "EML-000007",
      "sfn_email_id": "3aec4dfb-b152-45ce-9d56-3e3ddb1b65be",
      "gold_intent": "payment_issue",
      "gold_route_team": "finance_support_team",
      "gold_requires_human": true,
      "predicted_intent": "payment_issue",
      "predicted_urgency": "medium",
      "predicted_sentiment": "neutral",
      "predicted_route": "finance_support_team",
      "confidence_score": 0.6382,
      "action": "human_review",
      "response_text": "Dear Eoin,\n\nThank you for bringing your billing concern to our attention. To help us investigate this issue, could you please provide us with the following information:\n\n- Your policy number\n- The date of the transaction in question\n- The amount in question\n\nYou can find this information in your secure Member Area under the 'My Policy' or 'My Claims' section. If you have any difficulty accessing your Member Area, please contact us and we will be happy to assist you.\n\nOnce we have this informatio",
      "rag_hit_count": 5,
      "crm_found": false,
      "crm_policy_status": "",
      "crm_plan_name": "",
      "crm_eligible": false,
      "extracted_policy": "",
      "extracted_member": "",
      "pii_detected": false,
      "medical_detected": false,
      "exec_status": "SUCCEEDED",
      "exec_error": null
    },
    {
      "laya_email_id": "EML-000009",
      "sfn_email_id": "6c3c8e81-e533-4dcb-82fa-3eb9392d9899",
      "gold_intent": "claim_status",
      "gold_route_team": "claims_team",
      "gold_requires_human": true,
      "predicted_intent": "claim_status",
      "predicted_urgency": "medium",
      "predicted_sentiment": "positive",
      "predicted_route": "claims_team",
      "confidence_score": 0.5988,
      "action": "human_review",
      "response_text": "Dear Ryan,\n\nThank you for contacting Laya Healthcare regarding the status of your claim CLM-950666. We have received your claim and are currently reviewing the documentation provided. Once we have all necessary information, we will process your claim as soon as possible.\n\nIn the meantime, you can check the status of your claim online through your Member Area at https://www.layahealthcare.ie/memberarea/howtousememberarea.\n\nIf you have any further questions, please do not hesitate to contact us at",
      "rag_hit_count": 5,
      "crm_found": false,
      "crm_policy_status": "",
      "crm_plan_name": "",
      "crm_eligible": false,
      "extracted_policy": "POL-IE-938403",
      "extracted_member": "",
      "pii_detected": false,
      "medical_detected": true,
      "exec_status": "SUCCEEDED",
      "exec_error": null
    },
    {
      "laya_email_id": "EML-000010",
      "sfn_email_id": "5b0cb493-f452-44c1-9ce6-76e01857b661",
      "gold_intent": "claim_submission",
      "gold_route_team": "claims_team",
      "gold_requires_human": false,
      "predicted_intent": "claim_submission",
      "predicted_urgency": "medium",
      "predicted_sentiment": "positive",
      "predicted_route": "claims_team",
      "confidence_score": 0.8088,
      "action": "auto_response",
      "response_text": "Dear Conor,\n\nThank you for contacting Laya Healthcare regarding your claim for an antibiotic prescription on 31 May 2025 at Liffey Pharmacy. To process your claim, please follow these steps:\n\n1. Download the Laya App or go online to your Member Area.\n2. Submit your claim through the App or Member Area by taking a photo of your receipt and following the instructions provided.\n\nYour policy number is POL-IE-689107 and your Member ID is MEM-000132.\n\nIf you have any questions or need assistance, plea",
      "rag_hit_count": 5,
      "crm_found": false,
      "crm_policy_status": "",
      "crm_plan_name": "",
      "crm_eligible": false,
      "extracted_policy": "POL-IE-689107",
      "extracted_member": "MEM-000132",
      "pii_detected": false,
      "medical_detected": true,
      "exec_status": "SUCCEEDED",
      "exec_error": null
    },
    {
      "laya_email_id": "EML-000013",
      "sfn_email_id": "e5268f18-3513-4096-9359-f2fd38224b82",
      "gold_intent": "claim_submission",
      "gold_route_team": "claims_team",
      "gold_requires_human": false,
      "predicted_intent": "claim_submission",
      "predicted_urgency": "medium",
      "predicted_sentiment": "positive",
      "predicted_route": "claims_team",
      "confidence_score": 0.6122,
      "action": "human_review",
      "response_text": "Dear Sean,\n\nThank you for submitting your root canal consultation claim for EUR 651.53 on 06 February 2026 at Cork Dental Centre. We have received your invoice and receipt. Your policy number is POL-IE-222621 and your Member ID is MEM-000529. To ensure a smooth processing of your claim, please note that you can manage your policy, check your cover, and submit claims online through our Member Area or Laya App 24/7.\n\nFor further assistance, please contact our Customer Service Team at +353 1 234 56",
      "rag_hit_count": 5,
      "crm_found": false,
      "crm_policy_status": "",
      "crm_plan_name": "",
      "crm_eligible": false,
      "extracted_policy": "POL-IE-222621",
      "extracted_member": "MEM-000529",
      "pii_detected": false,
      "medical_detected": false,
      "exec_status": "SUCCEEDED",
      "exec_error": null
    },
    {
      "laya_email_id": "EML-000012",
      "sfn_email_id": "790e8b2b-bfcc-4d04-b7d3-fa2cdd2fbd98",
      "gold_intent": "coverage_query",
      "gold_route_team": "customer_support_team",
      "gold_requires_human": true,
      "predicted_intent": "coverage_query",
      "predicted_urgency": "medium",
      "predicted_sentiment": "neutral",
      "predicted_route": "medical_review_team",
      "confidence_score": 0.816,
      "action": "auto_response",
      "response_text": "Dear Padraig,\n\nThank you for contacting Laya Healthcare regarding your upcoming cardiology review appointment at Beacon Medical Centre on 17 April 2025. Based on the information available to us, we can confirm that Heartbeat Cardiac Screening, which includes a cardiologist review, is covered under your current plan as outlined in our Knowledge Base articles on 'Your Member Benefits | Laya Healthcare Ireland' and 'Cardiac | Your Member Benefits | Laya Healthcare Ireland'. However, please note tha",
      "rag_hit_count": 5,
      "crm_found": false,
      "crm_policy_status": "",
      "crm_plan_name": "",
      "crm_eligible": false,
      "extracted_policy": "POL-IE-761685",
      "extracted_member": "",
      "pii_detected": false,
      "medical_detected": false,
      "exec_status": "SUCCEEDED",
      "exec_error": null
    },
    {
      "laya_email_id": "EML-000011",
      "sfn_email_id": "9bebb476-75c8-457d-ae4e-9c285f01acd8",
      "gold_intent": "id_verification",
      "gold_route_team": "operations_team",
      "gold_requires_human": true,
      "predicted_intent": "id_verification",
      "predicted_urgency": "medium",
      "predicted_sentiment": "positive",
      "predicted_route": "customer_support_team",
      "confidence_score": 0.5185,
      "action": "human_review",
      "response_text": "\n\n{\n  \"response_text\": \"Dear Eoin,\\\\\n\nThank you for submitting your identification documents to verify the details of your policy POL-IE-872399. We appreciate your cooperation in this matter.\\\\\n\nYour documents have been received and will be processed as soon as possible. Once verified, your account details will be updated accordingly.\\\\\n\nIf you have any further queries or concerns, please do not hesitate to contact us.\\\\\n\nBest regards,\\\\\n[Your Name]\\\\\nCustomer Service Agent\\\\\n[Company Name]\",\n  ",
      "rag_hit_count": 5,
      "crm_found": false,
      "crm_policy_status": "",
      "crm_plan_name": "",
      "crm_eligible": false,
      "extracted_policy": "POL-IE-872399",
      "extracted_member": "",
      "pii_detected": false,
      "medical_detected": false,
      "exec_status": "SUCCEEDED",
      "exec_error": null
    },
    {
      "laya_email_id": "EML-000015",
      "sfn_email_id": "356848a5-ee6e-414b-8f59-26f8a239c100",
      "gold_intent": "claim_status",
      "gold_route_team": "claims_team",
      "gold_requires_human": false,
      "predicted_intent": "claim_status",
      "predicted_urgency": "medium",
      "predicted_sentiment": "positive",
      "predicted_route": "claims_team",
      "confidence_score": 0.7794,
      "action": "human_review",
      "response_text": "Dear Saoirse,\n\nThank you for contacting Laya Healthcare regarding the status of your claim with reference CLM-678850 and policy number POL-IE-658710. To check the current status of your claim, please log in to your Member Area or use the Laya App. You can easily submit and manage your claims 24/7, including taking a photo of your receipt for GP visits, physiotherapy, and other medical expenses. If you need any assistance with using the Member Area or the App, please don't hesitate to contact our",
      "rag_hit_count": 5,
      "crm_found": false,
      "crm_policy_status": "",
      "crm_plan_name": "",
      "crm_eligible": false,
      "extracted_policy": "POL-IE-658710",
      "extracted_member": "",
      "pii_detected": false,
      "medical_detected": false,
      "exec_status": "SUCCEEDED",
      "exec_error": null
    },
    {
      "laya_email_id": "EML-000018",
      "sfn_email_id": "eaf98d87-d840-4879-8bf0-d011e7f5a09a",
      "gold_intent": "renewal_query",
      "gold_route_team": "renewals_team",
      "gold_requires_human": false,
      "predicted_intent": "renewal_query",
      "predicted_urgency": "medium",
      "predicted_sentiment": "neutral",
      "predicted_route": "renewals_team",
      "confidence_score": 0.6362,
      "action": "human_review",
      "response_text": "Dear Liam,\n\nThank you for contacting Laya Healthcare regarding your renewal notice. We understand that the premium has increased compared to last year, and you are considering switching to a different plan.\n\nTo help you make an informed decision, we encourage you to explore our range of plans and benefits available on our website. You can use the Member Area to manage your policy, check your cover, and compare plans.\n\nIf you decide to switch plans, please follow the instructions provided in the ",
      "rag_hit_count": 5,
      "crm_found": false,
      "crm_policy_status": "",
      "crm_plan_name": "",
      "crm_eligible": false,
      "extracted_policy": "",
      "extracted_member": "MEM-000048",
      "pii_detected": false,
      "medical_detected": false,
      "exec_status": "SUCCEEDED",
      "exec_error": null
    },
    {
      "laya_email_id": "EML-000014",
      "sfn_email_id": "c231c904-33a4-4e5c-a955-9a094ef0f330",
      "gold_intent": "claim_status",
      "gold_route_team": "claims_team",
      "gold_requires_human": false,
      "predicted_intent": "claim_status",
      "predicted_urgency": "medium",
      "predicted_sentiment": "positive",
      "predicted_route": "claims_team",
      "confidence_score": 0.7707,
      "action": "human_review",
      "response_text": "Dear Cian,\n\nThank you for contacting us regarding the status of your claim CLM-598077. We have reviewed your inquiry and can confirm that your claim is currently under review. We will keep you updated as soon as a decision has been made. In the meantime, if you have any further questions or concerns, please do not hesitate to contact us.\n\nBest regards,\nYour Health Insurance Team\n\nPolicy Number: POL-IE-238205",
      "rag_hit_count": 5,
      "crm_found": false,
      "crm_policy_status": "",
      "crm_plan_name": "",
      "crm_eligible": false,
      "extracted_policy": "POL-IE-238205",
      "extracted_member": "",
      "pii_detected": false,
      "medical_detected": true,
      "exec_status": "SUCCEEDED",
      "exec_error": null
    },
    {
      "laya_email_id": "EML-000019",
      "sfn_email_id": "aba1046f-e846-49e4-8cb9-bdd64b60b934",
      "gold_intent": "policy_change",
      "gold_route_team": "policy_admin_team",
      "gold_requires_human": false,
      "predicted_intent": "policy_change",
      "predicted_urgency": "low",
      "predicted_sentiment": "positive",
      "predicted_route": "policy_admin_team",
      "confidence_score": 0.6205,
      "action": "human_review",
      "response_text": "Dear Ryan,\n\nThank you for contacting Laya Healthcare regarding the incorrect name recorded on your policy. To update your contact details, please log in to your secure Member Area and follow the steps below:\n1. Click on the 'Manage your policy' tab.\n2. Select 'Update personal details'.\n3. Enter your new details and click 'Save'.\nIf you encounter any difficulties, please do not hesitate to contact our Laya Healthcare Concierge team on 1800 200 529 or email us at [concierge@layahealthcare.ie](mail",
      "rag_hit_count": 5,
      "crm_found": false,
      "crm_policy_status": "",
      "crm_plan_name": "",
      "crm_eligible": false,
      "extracted_policy": "POL-IE-103353",
      "extracted_member": "",
      "pii_detected": false,
      "medical_detected": false,
      "exec_status": "SUCCEEDED",
      "exec_error": null
    },
    {
      "laya_email_id": "EML-000016",
      "sfn_email_id": "6092a8d9-a9d6-49b7-ba27-33b2bccf32c8",
      "gold_intent": "claim_submission",
      "gold_route_team": "claims_team",
      "gold_requires_human": false,
      "predicted_intent": "claim_submission",
      "predicted_urgency": "medium",
      "predicted_sentiment": "positive",
      "predicted_route": "claims_team",
      "confidence_score": 0.5421,
      "action": "human_review",
      "response_text": "Dear Jack,\n\nThank you for submitting your MRI contrast fee claim on 08 February 2025 at Mater Imaging. To process your claim, please follow these steps:\n1. Download the Laya App or go online and claim through your Member Area.\n2. Take a photo of the attached receipt using your phone and submit it through the App or online.\n3. Once your claim is processed, you will receive a notification and the payment will be made directly into your bank account.\n\nIf you have any questions or need assistance, p",
      "rag_hit_count": 5,
      "crm_found": false,
      "crm_policy_status": "",
      "crm_plan_name": "",
      "crm_eligible": false,
      "extracted_policy": "POL-IE-239449",
      "extracted_member": "MEM-000153",
      "pii_detected": false,
      "medical_detected": true,
      "exec_status": "SUCCEEDED",
      "exec_error": null
    },
    {
      "laya_email_id": "EML-000017",
      "sfn_email_id": "8b1d5260-4e07-4103-8b78-069f8ba01111",
      "gold_intent": "payment_issue",
      "gold_route_team": "finance_support_team",
      "gold_requires_human": false,
      "predicted_intent": "payment_issue",
      "predicted_urgency": "medium",
      "predicted_sentiment": "neutral",
      "predicted_route": "finance_support_team",
      "confidence_score": 0.7318,
      "action": "human_review",
      "response_text": "Dear Noah,\n\nThank you for contacting Laya Healthcare regarding your billing issue. We apologize for any inconvenience this may have caused you.\n\nTo help us better understand your query, could you please provide us with the following details:\n\n- Your policy number\n- The name of the treatment or procedure in question\n- The date of the treatment or procedure\n- The amount being disputed\n\nOnce we have this information, we will be happy to investigate the matter further and provide you with an update ",
      "rag_hit_count": 5,
      "crm_found": false,
      "crm_policy_status": "",
      "crm_plan_name": "",
      "crm_eligible": false,
      "extracted_policy": "",
      "extracted_member": "",
      "pii_detected": false,
      "medical_detected": false,
      "exec_status": "SUCCEEDED",
      "exec_error": null
    },
    {
      "laya_email_id": "EML-000020",
      "sfn_email_id": "ac9c517f-1ff4-4b6d-b2c4-87ab143abd19",
      "gold_intent": "policy_change",
      "gold_route_team": "policy_admin_team",
      "gold_requires_human": false,
      "predicted_intent": "policy_change",
      "predicted_urgency": "low",
      "predicted_sentiment": "positive",
      "predicted_route": "customer_support_team",
      "confidence_score": 0.8292,
      "action": "auto_response",
      "response_text": "Dear Emma,\n\nThank you for contacting us regarding your address update. We have received your request and will process the change to 27 Willow Park, Limerick as soon as possible. Once the change has been made, we will confirm the effective date and update your records accordingly. Your member ID and policy number will be recorded in the case notes for reference. If you have any further queries, please do not hesitate to contact us.\n\nBest regards,\nYour Health Insurance Team\n",
      "rag_hit_count": 5,
      "crm_found": false,
      "crm_policy_status": "",
      "crm_plan_name": "",
      "crm_eligible": false,
      "extracted_policy": "",
      "extracted_member": "",
      "pii_detected": false,
      "medical_detected": false,
      "exec_status": "SUCCEEDED",
      "exec_error": null
    }
  ]
}